goe/__init__.py
goe/__main__.py
goe/cli.py
goe/json_client.py
goe/charger/__init__.py
goe/charger/components.py
goe/charger/enums.py
goe/components/__init__.py
goe/components/client.py
goe/components/common.py
goe/components/component.py
goe/controller/__init__.py
goe/controller/components.py
goe-0.3.2.dist-info/METADATA
goe-0.3.2.dist-info/WHEEL
goe-0.3.2.dist-info/entry_points.txt
goe-0.3.2.dist-info/licenses/LICENSE
goe-0.3.2.dist-info/RECORD
