Metadata-Version: 2.4
Name: goe
Version: 0.3.2
Summary: API clients for go-e devices
Author-email: Michael Helmling <michaelhelmling@posteo.de>
License-Expression: MIT
License-File: LICENSE
Requires-Python: >=3.10
